emc/__init__.py
emc/emc.py
emc/lib/__init__.py
emc/lib/convert.py
emc/lib/frontend.py
emc/lib/logger.py
emc/lib/type.py
emc/lib/worker.py
emc/lib/wrapper.py
emc/lib/modifiers/ContentSecurityPolicyModifier.py
emc/lib/modifiers/ExecuteScriptModifier.py
emc/lib/modifiers/HostPermissionsModifier.py
emc/lib/modifiers/InsertCssModifier.py
emc/lib/modifiers/JSActionModifier.py
emc/lib/modifiers/ManifestActionModifier.py
emc/lib/modifiers/ManifestVersionModifier.py
emc/lib/modifiers/Modifier.py
emc/lib/modifiers/ServiceWorkerModifier.py
emc/lib/modifiers/WebAccessibleResourcesModifier.py
emc/lib/modifiers/__init__.py
emc/utils/__init__.py
emc/utils/arguments.py
emc/utils/unzip.py
emc/utils/zip.py
tests/__init__.py
tests/test_convert.py
tests/test_type.py
extension_manifest_converter-1.0.0.dist-info/LICENSE
extension_manifest_converter-1.0.0.dist-info/METADATA
extension_manifest_converter-1.0.0.dist-info/WHEEL
extension_manifest_converter-1.0.0.dist-info/entry_points.txt
extension_manifest_converter-1.0.0.dist-info/top_level.txt
extension_manifest_converter-1.0.0.dist-info/RECORD
